Metadata-Version: 2.1
Name: number-check
Version: 0.0.1
Summary: UNKNOWN
Home-page: UNKNOWN
Author: Apurba Khanra
Author-email: apurbakhanra@yahoo.com
License: MIT
Keywords: numbers,number,check number
Platform: UNKNOWN
Classifier: Development Status :: 5 - Production/Stable
Classifier: Intended Audience :: Education
Classifier: Operating System :: Microsoft :: Windows :: Windows 10
Classifier: License :: OSI Approved :: MIT License
Classifier: Programming Language :: Python :: 3
License-File: LICENCE.txt
